featomic/__init__.py
featomic/_c_api.py
featomic/_c_lib.py
featomic/basis.py
featomic/calculator_base.py
featomic/calculators.py
featomic/cutoff.py
featomic/density.py
featomic/log.py
featomic/profiling.py
featomic/splines.py
featomic/status.py
featomic/utils.py
featomic/version.py
featomic/_hypers/__init__.py
featomic/_hypers/_rascaline.py
featomic/clebsch_gordan/__init__.py
featomic/clebsch_gordan/_backend.py
featomic/clebsch_gordan/_cartesian_spherical.py
featomic/clebsch_gordan/_cg_product.py
featomic/clebsch_gordan/_coefficients.py
featomic/clebsch_gordan/_density_correlations.py
featomic/clebsch_gordan/_dispatch.py
featomic/clebsch_gordan/_equivariant_power_spectrum.py
featomic/clebsch_gordan/_equivariant_power_spectrum_by_pair.py
featomic/clebsch_gordan/_power_spectrum.py
featomic/clebsch_gordan/_utils.py
featomic/include/featomic.h
featomic/include/featomic.hpp
featomic/lib/libfeatomic.so
featomic/lib/cmake/featomic/featomic-config-version.cmake
featomic/lib/cmake/featomic/featomic-config.cmake
featomic/systems/__init__.py
featomic/systems/ase.py
featomic/systems/base.py
featomic/systems/chemfiles.py
featomic/systems/pyscf.py
featomic-0.6.3.dist-info/METADATA
featomic-0.6.3.dist-info/WHEEL
featomic-0.6.3.dist-info/top_level.txt
featomic-0.6.3.dist-info/zip-safe
featomic-0.6.3.dist-info/RECORD
featomic-0.6.3.dist-info/licenses/AUTHORS
featomic-0.6.3.dist-info/licenses/LICENSE
