Metadata-Version: 2.4
Name: featomic
Version: 0.6.3
Summary: Computing representations for atomistic machine learning
Author: Guillaume Fraux, Philip Loche, Sergei Kliavinek, Kevin Kazuki Huguenin-Dumittan, Davide Tisi, Alexander Goscinski
License-Expression: BSD-3-Clause
Project-URL: homepage, https://metatensor.github.io/featomic/latest/
Project-URL: documentation, https://metatensor.github.io/featomic/latest/
Project-URL: repository, https://github.com/metatensor/featomic
Keywords: computational science,machine learning,molecular modeling,atomistic representations
Classifier: Development Status :: 4 - Beta
Classifier: Intended Audience :: Science/Research
Classifier: Operating System :: POSIX
Classifier: Operating System :: MacOS :: MacOS X
Classifier: Operating System :: Microsoft :: Windows
Classifier: Programming Language :: Python
Classifier: Programming Language :: Python :: 3
Classifier: Topic :: Scientific/Engineering
Classifier: Topic :: Scientific/Engineering :: Bio-Informatics
Classifier: Topic :: Scientific/Engineering :: Chemistry
Classifier: Topic :: Scientific/Engineering :: Physics
Classifier: Topic :: Software Development :: Libraries
Classifier: Topic :: Software Development :: Libraries :: Python Modules
Requires-Python: >=3.9
License-File: LICENSE
License-File: AUTHORS
Requires-Dist: metatensor-core<0.2.0,>=0.1.15
Requires-Dist: metatensor-operations<0.4.0,>=0.3.0
Requires-Dist: wigners
Provides-Extra: torch
Requires-Dist: featomic-torch; extra == "torch"
Dynamic: author
Dynamic: license-file
Dynamic: provides-extra
